multiplierz/__init__.py
multiplierz/_msparser.pyd
multiplierz/fasta.py
multiplierz/internalAlgorithms.py
multiplierz/mass_biochem.py
multiplierz/msparser.py
multiplierz/mzGUI_standalone.py
multiplierz/mzml.py
multiplierz/post_process.py
multiplierz/settings.py
multiplierz/spectral_process.py
multiplierz/unimod.py
multiplierz/unimod.sqlite
multiplierz/mgf/__init__.py
multiplierz/mgf/extraction.py
multiplierz/mzAPI/D.py
multiplierz/mzAPI/__init__.py
multiplierz/mzAPI/bruker.py
multiplierz/mzAPI/management.py
multiplierz/mzAPI/mzML.py
multiplierz/mzAPI/mzMemo.py
multiplierz/mzAPI/mzT2D.py
multiplierz/mzAPI/mzURL.py
multiplierz/mzAPI/mzWiff.py
multiplierz/mzAPI/raw.py
multiplierz/mzAPI/agilentdlls/AgtFileSelectionDialog.dll
multiplierz/mzAPI/agilentdlls/AgtFileSelectionDialog.pdb
multiplierz/mzAPI/agilentdlls/BaseCommon.XML
multiplierz/mzAPI/agilentdlls/BaseCommon.dll
multiplierz/mzAPI/agilentdlls/BaseCommon.pdb
multiplierz/mzAPI/agilentdlls/BaseCommon.tlb
multiplierz/mzAPI/agilentdlls/BaseDataAccess.XML
multiplierz/mzAPI/agilentdlls/BaseDataAccess.dll
multiplierz/mzAPI/agilentdlls/BaseDataAccess.dll.config
multiplierz/mzAPI/agilentdlls/BaseDataAccess.pdb
multiplierz/mzAPI/agilentdlls/BaseDataAccess.tlb
multiplierz/mzAPI/agilentdlls/BaseError.XML
multiplierz/mzAPI/agilentdlls/BaseError.dll
multiplierz/mzAPI/agilentdlls/BaseError.pdb
multiplierz/mzAPI/agilentdlls/BaseTof.dll
multiplierz/mzAPI/agilentdlls/BaseTof.pdb
multiplierz/mzAPI/agilentdlls/Interop.shell32.dll
multiplierz/mzAPI/agilentdlls/MIDAC.XML
multiplierz/mzAPI/agilentdlls/MIDAC.dll
multiplierz/mzAPI/agilentdlls/MIDAC.pdb
multiplierz/mzAPI/agilentdlls/MassSpecDataReader.dll
multiplierz/mzAPI/agilentdlls/MassSpecDataReader.pdb
multiplierz/mzAPI/agilentdlls/MassSpecDataReader.tlb
multiplierz/mzAPI/agilentdlls/RegisterMassHunterDataAccess64.bat
multiplierz/mzAPI/agilentdlls/UnregisterMassHunterDataAccess64.bat
multiplierz/mzAPI/agilentdlls/agtsampleinforw.dll
multiplierz/mzAPI/agilentdlls/msvcp120.dll
multiplierz-2.2.2.dist-info/LICENSE
multiplierz-2.2.2.dist-info/METADATA
multiplierz-2.2.2.dist-info/WHEEL
multiplierz-2.2.2.dist-info/top_level.txt
multiplierz-2.2.2.dist-info/RECORD
