Metadata-Version: 2.1
Name: multiplierz
Version: 2.2.2
Summary: The MultiplierZ proteomics package
Author: William Max Alexander (et al.)
Author-email: williamM_alexander@dfci.harvard.edu
Keywords: biology bioinformatics proteomics spectrometry
Classifier: Development Status :: 4 - Beta
Classifier: Intended Audience :: Science/Research
Classifier: Topic :: Scientific/Engineering :: Bio-Informatics
Classifier: License :: OSI Approved :: GNU Lesser General Public License v2 or later (LGPLv2+)
Classifier: Programming Language :: Python
License-File: LICENSE
Requires-Dist: numpy
Requires-Dist: matplotlib
Requires-Dist: openpyxl
Requires-Dist: xlrd
Requires-Dist: xlwt
Requires-Dist: requests
Requires-Dist: beautifulsoup4
Requires-Dist: pythonnet (>=2.5.2)
Requires-Dist: pywin32 ; platform_system == "Windows"
Requires-Dist: comtypes ; platform_system == "Windows"
